kapak/__init__.py
kapak/aes.py
kapak/cli/__init__.py
kapak/cli/__main__.py
kapak/cli/arg.py
kapak/cli/cmd.py
kapak/cli/password.py
kapak/cli/pipe.py
kapak/cli/progress.py
kapak/cli/py.typed
kapak/error.py
kapak/key.py
kapak/py.typed
kapak/version.py
kapak-4.0.1.dist-info/METADATA
kapak-4.0.1.dist-info/WHEEL
kapak-4.0.1.dist-info/entry_points.txt
kapak-4.0.1.dist-info/licenses/LICENSE
kapak-4.0.1.dist-info/RECORD
