Metadata-Version: 2.4
Name: kapak
Version: 4.0.1
Summary: A simple-to-use file encryption script
License: Apache-2.0
License-File: LICENSE
Keywords: encryption,file encryption,encrypt file,aes,aes encryption,encryption script
Author: Amis Shokoohi
Author-email: amisshokoohi@gmail.com
Requires-Python: >=3.10,<4.0
Classifier: License :: OSI Approved :: Apache Software License
Classifier: Operating System :: OS Independent
Classifier: Programming Language :: Python :: 3
Classifier: Programming Language :: Python :: 3.10
Classifier: Programming Language :: Python :: 3.11
Classifier: Programming Language :: Python :: 3.12
Classifier: Programming Language :: Python :: 3.13
Classifier: Programming Language :: Python :: 3.14
Requires-Dist: cryptography (>=46.0.3,<47.0.0)
Project-URL: Homepage, https://github.com/amis-shokoohi/kapak
Project-URL: Repository, https://github.com/amis-shokoohi/kapak
